langchain_turbopuffer/__init__.py
langchain_turbopuffer-0.1.2.dist-info/LICENSE
langchain_turbopuffer-0.1.2.dist-info/METADATA
langchain_turbopuffer-0.1.2.dist-info/WHEEL
langchain_turbopuffer-0.1.2.dist-info/RECORD
