Metadata-Version: 2.1
Name: langchain-turbopuffer
Version: 0.1.2
Summary: an unofficial langchain binding for turbopuffer
License: MIT
Keywords: langchain,turbopuffer,vector-store
Author: Alex Chi Z
Author-email: iskyzh@gmail.com
Requires-Python: >=3.10,<3.13
Classifier: License :: OSI Approved :: MIT License
Classifier: Programming Language :: Python :: 3
Classifier: Programming Language :: Python :: 3.10
Classifier: Programming Language :: Python :: 3.11
Classifier: Programming Language :: Python :: 3.12
Requires-Dist: langchain (>=0.3.14,<0.4.0)
Requires-Dist: turbopuffer[fast] (>=0.1.25,<0.2.0)
